run_crom/__init__.py
run_crom/__main__.py
run_crom/callbacks.py
run_crom/cromnet.py
run_crom/run_crom.py
run_crom/simulation.py
run_crom/util.py
run_crom-1.0.0.dist-info/METADATA
run_crom-1.0.0.dist-info/WHEEL
run_crom-1.0.0.dist-info/entry_points.txt
run_crom-1.0.0.dist-info/top_level.txt
run_crom-1.0.0.dist-info/RECORD
