Metadata-Version: 2.1
Name: run-crom
Version: 1.0.0
Summary: A package for training and testing CROM weights
Home-page: https://github.com/dc3042/CROM_offline_training
Author: David Cho
Author-email: dc3042@columbia.edu
License: UNKNOWN
Platform: UNKNOWN
Classifier: Programming Language :: Python :: 3.7
Classifier: License :: OSI Approved :: GNU General Public License v3 (GPLv3)
Requires-Dist: h5py (==3.4.0)
Requires-Dist: numpy (>=1.22)
Requires-Dist: pynvml (==11.0.0)
Requires-Dist: pytorch-lightning (==1.6.5)
Requires-Dist: torch (==1.11.0)
